{
    "initial_capital": 1000000.0,
    "final_equity": 86799.99999999988,
    "total_return_pct": -91.32000000000001,
    "max_drawdown_pct": -91.32000000000001,
    "num_trades": 39,
    "win_rate_pct": 30.76923076923077,
    "profit_factor": 0.5649874955341193,
    "sharpe_ratio": -0.2119468539672683,
    "sortino_ratio": -0.13453057313725078,
    "cagr_pct": -99.91102070223303,
    "calmar_ratio": -1.0,
    "start_date": "2025-07-14 15:30:00",
    "end_date": "2025-11-18 15:30:00",
    "num_days": 127
}