{
    "initial_capital": 1000000.0,
    "final_equity": 1653850.0,
    "total_return_pct": 65.385,
    "max_drawdown_pct": -33.5288295883582,
    "num_trades": 106,
    "win_rate_pct": 45.28301886792453,
    "profit_factor": 1.2541839174295877,
    "sharpe_ratio": 0.24703249083505935,
    "sortino_ratio": 0.1914612457856205,
    "cagr_pct": 324.58171099909805,
    "calmar_ratio": 1.9501128074778618,
    "start_date": "2025-07-14 15:30:00",
    "end_date": "2025-11-18 15:30:00",
    "num_days": 127
}